tasq/__init__.py
tasq/tasq.py
tasq-0.0.3.dist-info/METADATA
tasq-0.0.3.dist-info/WHEEL
tasq-0.0.3.dist-info/entry_points.txt
tasq-0.0.3.dist-info/top_level.txt
tasq-0.0.3.dist-info/RECORD
