Metadata-Version: 2.1
Name: tasq
Version: 0.0.3
Summary: Task handlinlg.
Home-page: https://github.com/tmbdev/tasq
Author: Tom Breuel
Author-email: tmbdev+remove@gmail.com
License: UNKNOWN
Platform: UNKNOWN
Classifier: Programming Language :: Python :: 3
Classifier: License :: OSI Approved :: MIT License
Classifier: Operating System :: OS Independent
Requires-Python: >=3.6
Requires-Dist: jinja2
Requires-Dist: pyyaml
Requires-Dist: typer
Requires-Dist: braceexpand
